app/__init__.py
app/__main__.py
app/config.py
app/server.py
app/tracing.py
app/prompts/__init__.py
app/tools/__init__.py
app/tools/cache.py
app/tools/context.py
app/tools/demo.py
app/tools/health.py
app/tools/secrets.py
fastmcp_template-0.0.3.dist-info/METADATA
fastmcp_template-0.0.3.dist-info/WHEEL
fastmcp_template-0.0.3.dist-info/entry_points.txt
fastmcp_template-0.0.3.dist-info/licenses/LICENSE
fastmcp_template-0.0.3.dist-info/RECORD
