Metadata-Version: 2.4
Name: fastmcp-template
Version: 0.0.3
Summary: FastMCP server template with mcp-refcache and Langfuse tracing
Author-email: l4b4r4b4b4 <lucas.cansino@mail.de>
License-File: LICENSE
Requires-Python: >=3.12
Requires-Dist: fastmcp>=2.14.0
Requires-Dist: langfuse>=3.10.0
Requires-Dist: mcp-refcache>=0.1.0
Requires-Dist: pydantic-settings>=2.10.0
Requires-Dist: pydantic>=2.10.0
Requires-Dist: typer>=0.15.0
